{
    "HP":"Honors Physics",
    "APP1":"AP Physics 1",
    "APP2":"AP Physics 2",
    "APPC":"AP Physics C",
    "HC":"Honors Chemistry",
    "APC":"AP Chemistry",
    "HB":"Honors Biology",
    "APB":"AP Biology",

    "APELANG":"AP English Language",
    "APELIT": "AP English Literature",
    "LITCRIT": "Literary Criticism",

    "APS":"AP Statistics",
    "LINALG":"Linear Algebra",
    "DE":"Differential Equations",
    "MULTIVAR":"Multivariable Calculus",
    "APCAB":"AP Calculus AB",
    "APCBC":"AP Calculus BC",
    "GT":"Game Theory",
    "GTBE":"Game Theory and Behavioral Economics",
    "CORPFIN":"Corporate Finance",
    "ECONMET":"Econometrics",

    "APWH":"AP World History",
    "APEH":"AP European History",
    "HCPCS":"Honors Colonial and Post-Colonial Studies",

    "LATIN":"Latin",
    "SPANISH":"Spanish",
    "FRENCH":"French",
    "MANDARIN":"Mandarin",
    
    "L":"Lunch",

    "APCSA":"AP Computer Science A",
    "APCSP":"AP Computer Science Principles",
    "APECON":"AP Economics",
    "APPSY":"AP Psychology",
    "APMT":"AP Music Theory",
    "DP":"Digital Photography",
    "PJ":"Photojournalism",
    "AG":"Ancient Greek",
    "APSEM":"AP Seminar",
    "BIOTECH":"Biotechnology",
    "EE":"Empowering Entrepreneurs",
    "GUITAR":"Guitar",
    "PIANO":"Piano",

    "CCDIAZ":"Diaz College Counseling",
    "CCFILIOS":"Filios College Counseling",
    "CCMCOLLUM":"McCollum College Counseling",

    "LING":"Linguistics",
    "EXABS":"Existentialism and the Absurd",
    "RHETCOM":"Rhetoric and Communications",
    "PSYCHHM":"Psychology of Happiness and Mindreading",
    "AOV":"Anatomy of Violence",
    "MVFIC":"Multiversal Fiction",
    "TWIDEM":"Twilight of Democracy",

    "INDCHEM":"Industrial Chemistry",
    "JAVAML":"Advanced Java Topics and Machine Learning",
    "DEVGEN":"Developmental Genetics",
    "NEURO":"Neuroscience",
    "MOPHY":"Topics in Modern Physics",

    "APR":"AP Research"
}